[
    {
        "id": "pNIpCr03_nQ",
        "title": "祝！デビュー半年記念！初見さん大大大歓迎！雑談だけで12時間！プチ告知もある【 #南予りゅうか 】",
        "description": "おはよなんよ～！\nまだ半年しか経ってないの？と思いつつ、もう半年なの！？と驚きつつ\nこれからも自分のペースでやりたいように！\n\n★今回も序盤は【半年おめでとう】のコメントをしてくれた人の名前を書きます！\n色紙風画像企画は今回でラスト！\n初見さんも大歓迎！一言だけでもいいからコメントしてみてね✨\n\nぶいかふぇ♪NEXT vol.37\n詳細はこちら！\nhttps://jcm-event.bitfan.id/events/12868\n\nマシュマロも、良い\nhttps://marshmallow-qa.com/77qawruukjalkfq?t=lTK4gn&utm_medium=url_text&utm_source=promotion\n\n出来立て非公式wiki(リスナんよに特大の感謝を)\nhttps://w.atwiki.jp/nanyo-ryuka/\n\n━━━━━━ ◦ ✤ ◦ ━━━━━━\n\n待機中BGM: https://www.youtube.com/watch?v=nFwaJdZCHzM\n配信BGM: https://www.youtube.com/watch?v=GPM_P9lAqDc\n\n━━━━━━ ◦ ✤ ◦ ━━━━━━\n\nX(Twitter)\nhttps://x.com/dancedancePOWER\n\nlitlink\nhttps://lit.link/NanyoRyuka\n\nFANBOX\nhttps://nanyo.fanbox.cc/\n\nBOOTH\nhttps://nanyoryuka.booth.pm/\n\n━━━━━━ ◦ ✤ ◦ ━━━━━━\n\nご協力のお願い\n・コメント\n・高評価\n・共有ボタンからX等でURL共有\n\n気が向いた方はご協力お願いいたします！\nこれらは配信者を支える一番強い力です！\n盛ってないです！\n\n━━━━━━ ◦ ✤ ◦ ━━━━━━\n\n※守れるよね\n・コメ欄での暴言荒らし誹謗中傷はだめ。Xの鍵垢でならOK！\n・コメント欄でのリスナーさん同士の会話は控えてね\n・話の流れに関係ない他の配信者さんの名前を出さない\n・コメントをする時に他のリスナーさんが見ても不快にならないか一度確認すること！\n\n\n#個人勢Vtuber #新人Vuber",
        "published_at": "2025-08-23T00:23:22Z",
        "comments": [
            {
                "text_display": "半年おめでとうございます🎉<br><br><a href=\"https://www.youtube.com/watch?v=pNIpCr03_nQ&amp;t=86\">1:26</a><br>OPあけ<br><br><a href=\"https://www.youtube.com/watch?v=pNIpCr03_nQ&amp;t=42790\">11:53:10</a><br>終わりの挨拶",
                "text_original": "半年おめでとうございます🎉\n\n1:26\nOPあけ\n\n11:53:10\n終わりの挨拶"
            },
            {
                "text_display": "おつかれなんよ〜<br>めでたいめでたい🎉<br>ゆっくり休んでね〜",
                "text_original": "おつかれなんよ〜\nめでたいめでたい🎉\nゆっくり休んでね〜"
            },
            {
                "text_display": "半年記念12時間雑談<br>おつかれなんよ〜<br><br>デビュー半年おめでとう〜!!<br>これからもよろしくね〜",
                "text_original": "半年記念12時間雑談\nおつかれなんよ〜\n\nデビュー半年おめでとう〜!!\nこれからもよろしくね〜"
            }
        ],
        "stream_start": "2025-08-22T12:00:20Z"
    }
]